dmlearn/__init__.py
dmlearn/signal.py
dmlearn/tests/__init__.py
dmlearn/tests/test_signal.py
dmlearn-2025.0.2.dist-info/licenses/LICENSE
dmlearn-2025.0.2.dist-info/METADATA
dmlearn-2025.0.2.dist-info/WHEEL
dmlearn-2025.0.2.dist-info/top_level.txt
dmlearn-2025.0.2.dist-info/RECORD
